flip-flop-d-comp/design.sv
`timescale 1ns / 1ps

module d_flip_flop(
    input clk,  // Clock
    input d,    // Entrada de dados
    output reg q // Saída
);

// Lógica do flip-flop D
always @(posedge clk) begin
    q <= d;
end

endmodule

flip-flop-d-comp/testbench.sv
module testbench;

reg clk;
reg d;
wire q;

// Instanciação do flip-flop D
d_flip_flop uut(
    .clk(clk), 
    .d(d), 
    .q(q)
);

initial begin
    // Inicialização
    clk = 0;
    d = 0;

    // Dump de variáveis para o arquivo VCD
    $dumpfile("dump.vcd");
    $dumpvars(1);

    // Testes
    #10 d = 1;
    #10 d = 0;
    #10 d = 1;
    #10 d = 0;

    // Termina a simulação após um determinado período
    #50 $finish;
end

// Gerador de clock
always #5 clk = ~clk;

endmodule

flip-flop-d-comp/dump.vcd
$date
	Tue Dec 12 00:44:56 2023
$end
$version
	Icarus Verilog
$end
$timescale
	1ps
$end
$scope module testbench $end
$var wire 1 ! q $end
$var reg 1 " clk $end
$var reg 1 # d $end
$upscope $end
$enddefinitions $end
#0
$dumpvars
0#
0"
x!
$end
#5000
0!
1"
#10000
0"
1#
#15000
1!
1"
#20000
0"
0#
#25000
0!
1"
#30000
0"
1#
#35000
1!
1"
#40000
0"
0#
#45000
0!
1"
