flip-flop-d-desc/design.sv
module d_flip_flop_desc(d, clk, q, notq);
  input d, clk;
  output q, notq;

  wire w1, w2;

  // Combina d e clk
  nand U1(w1, d, clk);

  // Combina x e clk para comportamento de latch
  nand U2(w2, w1, clk);

  // Combina x e notq para produzir q
  nand U3(q, notq, w1);

  // Combina q e y para produzir qbar
  nand U4(notq, q, w2);
endmodule

flip-flop-d-desc/testbench.sv
module testbench;

  // Instancia o flip-flop D implementado com portas NAND
  d_flip_flop_desc df1(d, clk, q, notq);

  // Variáveis de entrada e saída
  reg d, clk;
  wire q, notq;

  initial begin
    // Grava os sinais em um arquivo de dump
    $dumpfile("dump.vcd");
    $dumpvars(1);

    // Inicializa variáveis
    clk = 0;
    d = 0;

    // Aplicação de estímulo no sinal de dados
    #50 d = 1;
    #50 d = 0;

    // Finaliza simulação após 150 unidades de tempo
    #50 $finish;
  end

  // Geração do sinal de clock
  always #2 clk = ~clk;
endmodule

flip-flop-d-desc/dump.vcd
$date
	Tue Dec 12 00:45:07 2023
$end
$version
	Icarus Verilog
$end
$timescale
	1s
$end
$scope module testbench $end
$var wire 1 ! notq $end
$var wire 1 " q $end
$var reg 1 # clk $end
$var reg 1 $ d $end
$upscope $end
$enddefinitions $end
#0
$dumpvars
0$
0#
x"
x!
$end
#2
0"
1!
1#
#4
0#
#6
1#
#8
0#
#10
1#
#12
0#
#14
1#
#16
0#
#18
1#
#20
0#
#22
1#
#24
0#
#26
1#
#28
0#
#30
1#
#32
0#
#34
1#
#36
0#
#38
1#
#40
0#
#42
1#
#44
0#
#46
1#
#48
0#
#50
0!
1"
1#
1$
#52
0#
#54
0!
1#
#56
0#
#58
0!
1#
#60
0#
#62
0!
1#
#64
0#
#66
0!
1#
#68
0#
#70
0!
1#
#72
0#
#74
0!
1#
#76
0#
#78
0!
1#
#80
0#
#82
0!
1#
#84
0#
#86
0!
1#
#88
0#
#90
0!
1#
#92
0#
#94
0!
1#
#96
0#
#98
0!
1#
#100
0#
0$
#102
0"
1!
1#
